GoSqlShujukuJiaochengFix1/README.md
GoSqlShujukuJiaochengFix1/__init__.py
GoSqlShujukuJiaochengFix1/__main__.py
GoSqlShujukuJiaochengFix1/file.epub
GoSqlShujukuJiaochengFix1/index.html
GoSqlShujukuJiaochengFix1/css/__init__.py
GoSqlShujukuJiaochengFix1/css/annotations.css
GoSqlShujukuJiaochengFix1/css/main.css
GoSqlShujukuJiaochengFix1/css/normalize.css
GoSqlShujukuJiaochengFix1/css/popup.css
GoSqlShujukuJiaochengFix1/font/__init__.py
GoSqlShujukuJiaochengFix1/font/fontello.eot
GoSqlShujukuJiaochengFix1/font/fontello.svg
GoSqlShujukuJiaochengFix1/font/fontello.ttf
GoSqlShujukuJiaochengFix1/font/fontello.woff
GoSqlShujukuJiaochengFix1/img/__init__.py
GoSqlShujukuJiaochengFix1/img/annotator-glyph-sprite.png
GoSqlShujukuJiaochengFix1/img/annotator-icon-sprite.png
GoSqlShujukuJiaochengFix1/img/apple-touch-icon.png
GoSqlShujukuJiaochengFix1/img/cancelfullscreen.png
GoSqlShujukuJiaochengFix1/img/close.png
GoSqlShujukuJiaochengFix1/img/fullscreen.png
GoSqlShujukuJiaochengFix1/img/loader.gif
GoSqlShujukuJiaochengFix1/img/menu-icon.png
GoSqlShujukuJiaochengFix1/img/save.png
GoSqlShujukuJiaochengFix1/img/saved.png
GoSqlShujukuJiaochengFix1/img/settings-s.png
GoSqlShujukuJiaochengFix1/img/settings.png
GoSqlShujukuJiaochengFix1/img/star.png
GoSqlShujukuJiaochengFix1/js/__init__.py
GoSqlShujukuJiaochengFix1/js/epub.js
GoSqlShujukuJiaochengFix1/js/epub.min.js
GoSqlShujukuJiaochengFix1/js/epub.min.map
GoSqlShujukuJiaochengFix1/js/hooks.min.js
GoSqlShujukuJiaochengFix1/js/hooks.min.map
GoSqlShujukuJiaochengFix1/js/reader.js
GoSqlShujukuJiaochengFix1/js/reader.js.map
GoSqlShujukuJiaochengFix1/js/reader.min.js
GoSqlShujukuJiaochengFix1/js/reader.min.map
GoSqlShujukuJiaochengFix1/js/hooks/__init__.py
GoSqlShujukuJiaochengFix1/js/hooks/extensions/__init__.py
GoSqlShujukuJiaochengFix1/js/hooks/extensions/highlight.js
GoSqlShujukuJiaochengFix1/js/libs/__init__.py
GoSqlShujukuJiaochengFix1/js/libs/jquery.min.js
GoSqlShujukuJiaochengFix1/js/libs/localforage.min.js
go_sql_shujuku_jiaocheng_fix1-2025.3.25.1.dist-info/METADATA
go_sql_shujuku_jiaocheng_fix1-2025.3.25.1.dist-info/WHEEL
go_sql_shujuku_jiaocheng_fix1-2025.3.25.1.dist-info/entry_points.txt
go_sql_shujuku_jiaocheng_fix1-2025.3.25.1.dist-info/top_level.txt
go_sql_shujuku_jiaocheng_fix1-2025.3.25.1.dist-info/RECORD
